fsdict/__init__.py
fsdict/cryptofiledict.py
fsdict/cryptosqldict.py
fsdict/filedict.py
fsdict/flightcryptofiledict.py
fsdict/flightcryptosqldict.py
fsdict/sqldict.py
fsdict-0.8.1.dist-info/LICENSE
fsdict-0.8.1.dist-info/METADATA
fsdict-0.8.1.dist-info/WHEEL
fsdict-0.8.1.dist-info/top_level.txt
fsdict-0.8.1.dist-info/RECORD
