Metadata-Version: 2.1
Name: fsdict
Version: 0.8.1
Summary: Mutable mappings persisted in the filesystem, encrypted if you want.
Home-page: https://github.com/polyrand/produtils
Author: Ricardo Ander-Egg Aguilar
Author-email: ricardo.anderegg@gmail.com
License: UNKNOWN
Platform: UNKNOWN
Classifier: Development Status :: 5 - Production/Stable
Classifier: License :: OSI Approved :: MIT License
Classifier: Operating System :: OS Independent
Classifier: Programming Language :: Python :: 3
Classifier: Programming Language :: Python :: 3 :: Only
Classifier: Programming Language :: Python :: 3.7
Classifier: Programming Language :: Python :: 3.8
Requires-Python: >=3.7
Requires-Dist: cryptography
